QbiPy/VERSION
QbiPy/__init__.py
QbiPy/helpers.py
QbiPy/dce_models/__init__.py
QbiPy/dce_models/active_uptake_model.py
QbiPy/dce_models/data_io.py
QbiPy/dce_models/dce_aif.py
QbiPy/dce_models/dibem.py
QbiPy/dce_models/tissue_concentration.py
QbiPy/dce_models/tofts_model.py
QbiPy/dce_models/two_cfm_model.py
QbiPy/dce_models/two_cxm_model.py
QbiPy/examples/__init__.py
QbiPy/examples/tofts_model_example.py
QbiPy/image_io/__init__.py
QbiPy/image_io/analyze_format.py
QbiPy/image_io/jim_io.py
QbiPy/image_io/nifti2dicom.py
QbiPy/image_io/xtr_files.py
QbiPy/t1_mapping/VFA.py
QbiPy/t1_mapping/__init__.py
QbiPy/tools/__init__.py
QbiPy/tools/madym_output_to_dicom.py
QbiPy/tools/mplwidget.py
QbiPy/tools/qbiqscene.py
QbiPy/tools/runner.py
QbiPy/tools/AIF_viewer/AIF_viewer.py
QbiPy/tools/AIF_viewer/AIF_viewer_tool.py
QbiPy/tools/AIF_viewer/__init__.py
QbiPy/tools/DCE_fit_viewer/DCE_fit_viewer.py
QbiPy/tools/DCE_fit_viewer/DCE_fit_viewer_tool.py
QbiPy/tools/DCE_fit_viewer/__init__.py
QbiPy/tools/simple_3D_viewer/__init__.py
QbiPy/tools/simple_3D_viewer/simple_3D_viewer.py
QbiPy/tools/simple_3D_viewer/simple_3D_viewer_tool.py
QbiPy-1.3.8.dist-info/LICENSE
QbiPy-1.3.8.dist-info/METADATA
QbiPy-1.3.8.dist-info/WHEEL
QbiPy-1.3.8.dist-info/top_level.txt
QbiPy-1.3.8.dist-info/RECORD
