Metadata-Version: 2.1
Name: QbiPy
Version: 1.3.8
Summary: DCE-MRI analysis code from the QBI lab, University of Manchester
Home-page: https://gitlab.com/manchester_qbi/manchester_qbi_public/qbipy
Author: Michael Berks
Author-email: michael.berks@manchester.ac.uk
License: UNKNOWN
Project-URL: Bug Tracker, https://gitlab.com/manchester_qbi/manchester_qbi_public/qbipy/-/issues
Platform: UNKNOWN
Classifier: Programming Language :: Python :: 3
Classifier: License :: OSI Approved :: Apache Software License
Classifier: Operating System :: OS Independent
Requires-Python: >=3.6
License-File: LICENSE
Requires-Dist: gitpython
Requires-Dist: numpy
Requires-Dist: scipy
Requires-Dist: scikit-image
Requires-Dist: PyQt5
Requires-Dist: nibabel
Requires-Dist: matplotlib
Requires-Dist: configargparse
Requires-Dist: pydicom
